setup.py
JomyTesting.egg-info/PKG-INFO
JomyTesting.egg-info/SOURCES.txt
JomyTesting.egg-info/dependency_links.txt
JomyTesting.egg-info/top_level.txt
JovyTesting/__init__.py
JovyTesting/jmaths/__init__.py
JovyTesting/jmaths/jmaths.py