Metadata-Version: 1.0
Name: JomyTesting
Version: 0.0.1
Summary: The testing package for Jomy
Home-page: UNKNOWN
Author: Muheko Nikolas
Author-email: UNKNOWN
License: UNKNOWN
Platform: UNKNOWN
